data_processing_phenocams_app/__init__.py
data_processing_phenocams_app/app.py
data_processing_phenocams_app/components.py
data_processing_phenocams_app/utils.py
data_processing_phenocams_app/version.py
data_processing_phenocams_app-0.1.5.dist-info/METADATA
data_processing_phenocams_app-0.1.5.dist-info/WHEEL
data_processing_phenocams_app-0.1.5.dist-info/RECORD
